khmersegment
