Metadata-Version: 2.1
Name: khmersegment
Version: 0.1.1
Summary: A Khmer word segmentation tool built for NIPTICT Khmer Word Segmentation CRF model.
Home-page: https://github.com/seanghay/khmersegment
Author: Seanghay Yath
Author-email: seanghay.dev@gmail.com
License: Apache License 2.0
Platform: UNKNOWN
Classifier: Programming Language :: Python :: 3
Classifier: Operating System :: OS Independent
Classifier: Intended Audience :: Developers
Classifier: Natural Language :: English
Requires-Python: >=3.7
